Metadata-Version: 2.1
Name: csaf-controls
Version: 0.2
Summary: Control Systems Analysis Framework
Home-page: https://github.com/GaloisInc/csaf
Author: Ethan Lew, Michal Podhradsky, Aditya Zutshi
Author-email: ethanlew16@gmail.com, mpodhradsky@galois.com, aditya.zutshi@galois.com
License: UNKNOWN
Platform: UNKNOWN
Classifier: Programming Language :: Python :: 3
Classifier: License :: OSI Approved :: BSD License
Classifier: Operating System :: OS Independent
Requires-Python: >=3.9
Requires-Dist: numpy (>=1.20.0)
Requires-Dist: numba (>=0.54.0)
Requires-Dist: matplotlib (>=3.4.3)
Requires-Dist: scipy (>=1.7.1)
Requires-Dist: GPyOpt (>=1.2.6)
Requires-Dist: tqdm (>=4.62.2)
Requires-Dist: onnxruntime (>=1.7.0)
Requires-Dist: pydot (>=1.4.1)
Requires-Dist: svgpath2mpl (>=1.0.0)
